torch_resnet/__init__.py
torch_resnet/avg_2d.py
torch_resnet/init.py
torch_resnet/preact_resnet.py
torch_resnet/py.typed
torch_resnet/resnet.py
torch_resnet/shortcut.py
torch_resnet/utils.py
torch_resnet-0.0.4.dist-info/LICENSE
torch_resnet-0.0.4.dist-info/METADATA
torch_resnet-0.0.4.dist-info/WHEEL
torch_resnet-0.0.4.dist-info/top_level.txt
torch_resnet-0.0.4.dist-info/RECORD
